[{"model": "viewer.genre", "pk": 1, "fields": {"name": "Akční"}}, {"model": "viewer.genre", "pk": 2, "fields": {"name": "Komedie"}}, {"model": "viewer.genre", "pk": 3, "fields": {"name": "Drama"}}, {"model": "viewer.genre", "pk": 4, "fields": {"name": "Animovaný"}}, {"model": "viewer.genre", "pk": 5, "fields": {"name": "Thriler"}}, {"model": "viewer.movie", "pk": 1, "fields": {"title_orig": "Forrest Gump", "title_cz": null, "title_sk": null, "movie_image": "", "year": 1993, "video": null, "description": "Poněkud prostoduchý Forrest Gump, vyzbrojen užitečnými radami své matky, se vydává na pouť životem, který mu připraví nejedno překvapení. Mnoho hořkých, ale také nádherných chvil...\r\nMladý muž jménem Forrest Gump sedí na zastávce autobusu a každému, kdo si přisedne, vypráví o svém životě. Poněkud jednoduchý chlapec se narodil v Alabamě, kde žil jen s matkou, která mu dala mnoho dobrých rad do života. Především tu, aby si nikdy nenechal od nikoho namluvit, že je jiný než ostatní. Dostala ho dokonce i do normální školy, přestože jí doporučovali zvláštní, vzhledem k jeho nízkému IQ. Forrest, terč zlomyslných vtípků a krutých žertů svých kamarádů, si tam najde přítelkyni na celý život: Jenny je půvabná blonďatá holčička, kterou zneužívá otec, a tak ji dají do výchovy babičce. Oba se stanou nerozlučnými přáteli. Jenny Forrestovi dá další cennou radu do života: když budeš mít problém, utíkej. A tak Forrest proutíká školou, pak i střední školou a nakonec vysokou, kde se osvědčí jako nejrychlejší hráč amerického fotbalu. Po svém prožívá i velké události v amerických dějinách, třeba přijetí dvou prvních černých studentů na univerzitu nebo setkání s prezidentem Kennedym... Forrest se na vše dívá svýma naivníma očima, aniž by věci zvažoval do důsledků. Řídí se upřímným citem, jako když stále a opakovaně „zachraňuje“ Jenny, jakmile se mu zdá, že jí někdo ubližuje. Když získá diplom, dá se naverbovat do armády. Doslechne se, že Jenny vyhodili ze školy kvůli nestoudným fotkám a že se pokouší v Memphisu prosadit jako zpěvačka. Navštíví ji a znovu nešikovně „zachraňuje“. Pak je poslán do Vietnamu. Ani hrůzy války tak docela nechápe, i když se při jednom útoku projde dokonalým peklem. Je zabit jeho zatím jediný přítel, černoch Bubba. Forrest, kterého chtěl Bubba přibrat jako partnera do své firmy, je zdrcený. Přesto zachrání několik dalších vojáků včetně poručíka Dana Taylora, který mu ale není pranic vděčný: jakožto člen rodiny, v níž celé generace mužů umíraly ve válkách, si přeje zemřít po boku svých mužů. A on navíc přijde o obě nohy. Zraněn je ale i Forrest a vrací se domů. Ještě ve Vietnamu v nemocnici se mu vrátí dopisy, které pravidelně psal Jenny a jejichž adresátka nebyla zastižena... Po návratu domů mu prezident Johnson udělí medaili a při prohlídce Washingtonu se přimíchá do davu protestujících proti válce. Je vyzván, aby pohovořil o Vietnamu, nejde ale zvuk. Přesto ho tisícihlavý dav zdraví jako hrdinu. Mezi přihlížejícími je i Jenny, nyní horlivá aktivistka protiválečného hnutí Černí panteři. Shledání Forresta s jeho velkou a jedinou láskou je dojemné. Prochodí spolu celou noc a povídají si. Forrest nechce, aby Jenny opět odjela, ale ta se chystá do Kalifornie. Forrest zůstává zase sám...", "created": "2023-12-14T16:48:49.371Z", "updated": "2023-12-14T16:48:49.371Z", "countries": [], "genres": [], "directors": [], "actors": []}}, {"model": "viewer.movie", "pk": 2, "fields": {"title_orig": "Intouchables", "title_cz": null, "title_sk": null, "movie_image": "", "year": 2011, "video": null, "description": "Ochrnutý a bohatý aristokrat Philippe si za svého nového opatrovníka vybere Drisse, živelného mladíka z předměstí, kterého právě propustili z vězení. Jinými slovy - najde si na tuto práci tu nejméně vhodnou osobu. Podaří se jim však propojit nemožné: Vivaldiho a populární hudbu, serióznost a žoviální vtípky, luxusní obleky a tepláky. Bláznivým, zábavným, silným, neočekávaným a hlavně „nedotknutelným“, přesně takovým se stane jejich přátelství… Komedie s dramatickou zápletkou o tom, že ani od krku po prsty u nohou nepohyblivý člověk odkázaný na pomoc druhých, nemusí ztratit smysl života. A o tom, že i nejméně pravděpodobné spojení melancholického multimilionáře a extrovertního recidivisty může humorně zapůsobit na diváka a může se z něj stát kasovní trhák.", "created": "2023-12-14T16:49:10.349Z", "updated": "2023-12-14T16:49:10.349Z", "countries": [], "genres": [], "directors": [], "actors": []}}, {"model": "viewer.movie", "pk": 3, "fields": {"title_orig": "One Flew over the Cuckoo's Nest", "title_cz": null, "title_sk": null, "movie_image": "", "year": 1975, "video": null, "description": "Předlohou k filmu Přelet nad kukaččím hnízdem byl režiséru Miloši Formanovi román Kena Keseyho, který ho psal při působení v „nemocnici pro veterány“. Snímek se stal největším mezinárodním úspěchem ve Formanově kariéře. V roce 1976 získal Oscara ve všech hlavních kategoriích – za nejlepší film, režii, mužský herecký výkon (Jack Nicholson), ženský herecký výkon (Louise Fletcherová) a scénář. Majitelem filmových a divadelních práv byl 13 let Kirk Douglas, který je postoupil svému synu Michaelovi a tím z něho udělal úspěšného producenta... Zrzavý irský rváč a profesionální karbaník Randle Patrick McMurphy si odpykává trest za opakované násilné napadení a sexuální zneužití. Místo aby se držel v pracovním táboře, hraje pomateného a nechá se poslat do zdánlivého klidu psychiatrické léčebny. Jeho životní elán a silná osobnost se v ústavu brzy střetávají s absolutismem vrchní sestry Ratchedové, která s pomocí trojice lapiduchů tyransky vládne celému ústavu. McMurphy nesnese pohled na ušlápnuté pacienty a brzy v nich probouzí poslední špetku hrdosti a radosti ze života. V zápasu s Velkou sestrou obrátí blázinec doslova vzhůru nohama. Stěny ústavu se otřásají jeho hřmotným smíchem a nespoutaným elánem. Vzpoura McMurphyho ale nemá velkou naději proti síle mašinérie zosobněné Velkou sestrou… Brilantní románová satira Kena Keseyho, mísící v sobě komiku i tragiku, přerůstá v neobyčejně působivém filmovém zpracování v silný protest proti neomezené moci a omezování každého člověka.", "created": "2023-12-14T16:49:32.289Z", "updated": "2023-12-14T16:49:32.289Z", "countries": [], "genres": [], "directors": [], "actors": []}}, {"model": "viewer.movie", "pk": 4, "fields": {"title_orig": "Pelíšky", "title_cz": null, "title_sk": null, "movie_image": "", "year": 1999, "video": null, "description": "A je tu zpět jedna z nejúspěšnějších českých filmových komedií od renomovaných tvůrců - režiséra J. Hřebejka a scenáristy P. Jarchovského s řadou skvělých herců. Vraťme se tedy s oblíbenými postavami k rodinným rituálům, láskám a trapasům odehrávajícím se na sklonku šedesátých let minulého století v jedné pražské čtvrti. Jemná poetika a humorná nadsázka jsou charakteristické pro vyprávění životních osudů tří generací mužů a žen ve zvláštním období našich dějin v roce 1968… V jedné dvoupatrové vile tu žijí dvě rodiny - Šebkovi a Krausovi. Otec Šebek (M. Donutil), prostoduchý, ale dobrácký důstojník z povolání, je zastáncem panujícího režimu a stejně vehementně obhajuje i vlastní neomylnost v roli hlavy rodiny. Elegantní otec Kraus (J. Kodet), bývalý odbojář s trpkou válečnou zkušeností, je naopak zarytým opozičníkem. Také on je přesvědčený o tom, že má za všech okolností pravdu - není proto divu, že se tihle dva nemají zrovna v lásce. Jejich děti - gymnazista Michal (M. Beran) a jeho spolužačka Jindřiška (K. Nováková) - spolu vycházejí docela dobře. I když Michal by byl rád, kdyby ho jeho sousedka brala trochu víc na vědomí. Ta má ale oči pro jiného. Nezbývá mu tedy nic jiného, než aby smutně přihlížel, jak mu jeho první milostné body krade spolužák Elien (O. Brousek). U Šebků a Krausů se zatím střídají rodinné návštěvy, ve vší obřadnosti se tu slaví Vánoce, svatba i nečekaný, bolestný pohřeb. Do zabydlených domácností vtrhnou i některé novodobé vymoženosti v podobě umělohmotných lžiček, nerozbitných sklenic i podivných her pro statečné pionýry. Mládež zatím pokukuje po lákadlech světa kapitalismu a snaží se žít svůj vlastní, na rodičovských autoritách a \"velké\" historii nezávislý život. V soukromí rodinných pelíšků se tak čas od času odehrají malá dramata názorů a vztahů, která se v paměti jejich účastníků otisknou už nejspíš navždy…", "created": "2023-12-14T16:49:49.942Z", "updated": "2023-12-14T16:49:49.942Z", "countries": [], "genres": [], "directors": [], "actors": []}}, {"model": "viewer.movie", "pk": 5, "fields": {"title_orig": "Schindler's List", "title_cz": null, "title_sk": null, "movie_image": "", "year": 1993, "video": null, "description": "Hluboce šokující, nemilosrdné drama o noční můře holocaustu, založené na skutečných událostech. Na záchranu 1100 životů obětoval Oskar Schindler veškeré své jmění... Polský Krakov 1939. Židovská obec je vystavována stále se zvyšujícímu tlaku ze strany nacistů. Do této vřavy vstupuje obchodník Oskar Schindler, člen Nacistické strany, velký svůdník a muže vydělávající na válečném utrpení, který dokázal najít v sobě člověka a zachránit ty, kterým už zdánlivě nebylo pomoci... Film Stevena Spielberga je stěžejní dílo světové kinematografie a vítěz sedmi Oscarů, včetně ocenění za Nejlepší film roku a Nejlepší režii.", "created": "2023-12-14T16:50:12.589Z", "updated": "2023-12-14T16:50:12.589Z", "countries": [], "genres": [], "directors": [], "actors": []}}, {"model": "viewer.movie", "pk": 6, "fields": {"title_orig": "Se7en", "title_cz": null, "title_sk": null, "movie_image": "", "year": 1995, "video": null, "description": "Dva policisté (Brad Pitt a Morgan Freeman) jsou na stopě geniálního vraha, zodpovědného za sérii děsivých vražd, jejichž oběti spojuje sedm smrtelných hříchů. V jedné z rolí tohoto kvalitního trhilleru, zasazeného do temného města nasáklého bolestí a zkázou, uvidíte také Gwyneth Paltrow. David Fincher (Klub rváčů, Zodiac, Podivuhodný případ Benjamina Buttona) s dokonalou znalostí našich nejhlubších obav pevně svírá otěže akce – fyzické, psychické i spirituální – neodvratně směřující k rozuzlení, které do hloubi otřese i tou nejzatvrzelejší duší.", "created": "2023-12-14T16:50:27.009Z", "updated": "2023-12-14T16:50:27.009Z", "countries": [], "genres": [], "directors": [], "actors": []}}, {"model": "viewer.movie", "pk": 7, "fields": {"title_orig": "The Godfather", "title_cz": null, "title_sk": null, "movie_image": "", "year": 1972, "video": null, "description": "Gangsterské drama Kmotr, natočené podle stejnojmenného bestselleru Maria Puza, patří mezi přelomová díla tzv. Nového Hollywoodu, a to jak komerčně, tak umělecky. Příběh newyorské mafiánské rodiny Corleonů, jíž tvrdou rukou šéfuje starý don Vito (Marlon Brando), se odehrává v letech 1945 - 55 a zaznamenává prudký rozmach organizovaného zločinu po skončení druhé světové války. V epických, rozmáchlých obrazech před divákem ožívají osudy italsko-americké rodiny, jež svůj blahobyt založila na hazardu, prostituci, vydírání a zastrašování. Tehdy mladý režisér Francis Ford Coppola, který byl poněkud překvapivě pověřen společností Paramount realizací jednoho z jejích stěžejních projektů (své nepochybně sehrálo i jeho italsko-americké zázemí), musel redukovat některé motivy rozsáhlé předlohy, ovšem podařilo se mu věrně zachovat jejího ducha - přesný popis fungování zločinecké organizace, zachycení její hierarchie, začlenění do tehdejšího společenského vývoje i často kritizované zdůrazňování rodinné soudržnosti. Pevnou dramatickou stavbu scénáře (na němž Coppola spolupracoval s autorem předlohy) podpořilo i režijní ztvárnění, jež čerpalo především z klasických vypravěčských praktik hollywoodských děl 30. let (např. Jih proti Severu), okořeněných soudobým příklonem k realismu, zejména v zobrazování násilí a sexu. Snímek získal tři Oscary - za nejlepší film, scénář podle předlohy a mužský herecký výkon v hlavní roli (Marlon Brando, který svou cenu odmítl převzít). Pro úspěch filmu, který se stal diváckým hitem nejen ve Spojených státech, ale i ve zbytku světa (kromě např. tehdejšího Československa, kde se kvůli údajné glorifikaci zločinu a násilí nesměl promítat, ač Puzova kniha v českém překladu vyšla), bylo klíčové herecké obsazení hlavních úloh dona Vita Corleona a jeho nejmladšího syna Michaela. Vedení Paramountu nesouhlasilo s Marlonem Brandem, na němž mu vedle jeho dobře známé pověsti \"obtížného a nespolehlivého herce, jehož poslední filmy byly propadáky\", vadilo hlavně to, že je na roli mafiánského patriarchy příliš mladý (v době příprav filmu mu bylo 47 let), a ještě větší odpor dávalo najevo vůči Al Pacinovi, jenž se jim zdál málo známý, příliš obyčejný a především malý. Coppola s oběma herci natočil testy, jež nakonec šéfy Paramountu přesvědčily. Se stejnou pečlivostí režisér obsadil i další role, nejstaršího Corleonova syna, prchlivého Sonnyho (James Caan), jeho slabošského bratra Freda (John Cazale) a conseglieriho Toma Hagena (Robert Duvall). Úlohy Corleonových \"vojáků\" a dalších gangsterů ztělesnili vesměs málo známí představitelé, kteří dokonale typově odpovídali svým postavám (např. Richard Castellano jako Clemenza nebo Al Lettieri jako Sollozzo). V kreaci Michaelovy neitalské dívky Kay Adamsové zaujala budoucí múza Woodyho Allena Diane Keatonová a Corleonovu týranou dceru Connii ztělesnila pozdější Stalloneova partnerka z Rockyho, Coppolova mladší sestra Talia Shireová. Téměř tříhodinový snímek (který uvádíme, stejně jako další díly trilogie, ve dvou částech) vrcholí slavnou scénou křtu Michaelova synovce (představovaného Coppolovou dcerou Sofií), prostříhaného krvavým vyřizováním účtů s ostatními mafiánskými rodinami, jež znamenalo upevnění moci Corleonova klanu, ale také definitivní převzetí \"rodinné firmy\" zprvu zdráhavým Michaelem, který se stává důstojným nástupcem zemřelého otce.", "created": "2023-12-14T16:50:48.404Z", "updated": "2023-12-14T16:50:48.404Z", "countries": [], "genres": [], "directors": [], "actors": []}}, {"model": "viewer.movie", "pk": 8, "fields": {"title_orig": "The Godfather: Part II", "title_cz": null, "title_sk": null, "movie_image": "", "year": 1974, "video": null, "description": "Jsme větší než U. S. Steel. Al Pacino a Robert De Niro v hlavních rolích pokračování slavné mafiánské ságy, oceněné šesti Oscary... Mimořádný úspěch Kmotra (1972) ve světových kinech logicky vedl k okamžitým úvahám o natočení pokračování, k němuž koneckonců vybízel i relativně otevřený konec originálu. Coppola, který tímto snímkem získal v Hollywoodu nesmírný respekt, ovšem nejdřív svého vlivu využil k realizaci osobního projektu Rozhovor (vyznamenaného mj. Zlatou palmou na MFF v Cannes, ale komerčně neúspěšného). Scénář Kmotra II, jenž je znovu společným dílem autora původní předlohy a režiséra, rozvíjí dvě dějové linie. Další osudy nového kmotra Michaela Corleona (Al Pacino), ovládajícího své impérium z rozsáhlého sídla v nevadském Lake Tahoe. A začátky mladého Vita Corleona (Robert De Niro) v New Yorku 20. let, jež jsou obsaženy i v Puzově původní knize. Michael musí čelit nejen svým konkurentům z podsvětí, zejména Hymanu Rothovi (pozoruhodná kreace slavného hereckého pedagoga Lee Strasberga), který využívá informací zhrzeného Michaelova bratra Freda (John Cazale), ale také zvýšenému zájmu orgánů spravedlnosti, jež v průběhu druhé poloviny 50. let, kdy se Kmotr II odehrává, zintenzivnily svou kampaň proti organizovanému zločinu. Michael své obchodní zájmy uhájí, přes nedobrovolné opuštění hazardních aktivit na revoluční Kubě, ovšem cena je vysoká. Předčasně zestárlý, zahořklý kmotr je ještě nelítostnějším šéfem než jeho otec, ale rodinné vazby, tvořící páteř prvního filmu, zmizely. Michael zůstává osamocený. Bez bratra, kterého nechal zabít, i bez manželky, která od něho odešla... Kmotr II je stejně výjimečným dílem jako originál, na který navazuje. Mnozí dokonce tvrdí, že lepším. Coppola se tu jako režisér představuje ve špičkové formě, navíc posílené neotřesitelným postavením režisérské hvězdy. Už nemusel bojovat o výši rozpočtu jako v případě prvního filmu (který se z finančních důvodů měl původně odehrávat v současnosti), ani o herce, jež hodlal angažovat. Ve všem měl naprosto volnou ruku. Prozřetelným se ukázalo obsazení málo známého Roberta De Nira jako mladého Vita Corleona, jehož elektrizující herectví tu získává na přesvědčivosti také citlivým využitím sicilského dialektu, který v raných scénách nahrazuje angličtinu. Jeho osud v nové zemi, kam musel uprchnout ze sicilské vesničky, jež mu dala jméno, ostře kontrastuje s údělem jeho syna. Vito buduje svoji pozici prakticky z ničeho, dokáže využít každé příležitosti, neštítí se násilných prostředků, pokud je považuje za nutné a efektivní, ale základem je pro něho rodina. Pokračování Kmotra se stalo prvním \"sequelem\", který získal Cenu Akademie za nejlepší film. Nezůstalo ovšem u jediného Oscara. Kmotr II v tomto ohledu překonal originál celkem se šesti soškami; další cenu mu Akademie udělila za nejlepší režii (ta Coppolovi v prvním případě unikla ve prospěch Boba Fosseho za Kabaret), scénář, výpravu, hudbu (slavný italský skladatel Nino Rota, opominutý u prvního dílu kvůli zařazení již použitých motivů z jiného filmu, tady spolupracoval s režisérovým otcem Carminem Coppolou) a konečně za fenomenální De Nirův výkon ve vedlejší roli.", "created": "2023-12-14T16:51:02.105Z", "updated": "2023-12-14T16:51:02.105Z", "countries": [], "genres": [], "directors": [], "actors": []}}, {"model": "viewer.movie", "pk": 9, "fields": {"title_orig": "The Green Mile", "title_cz": null, "title_sk": null, "movie_image": "", "year": 1999, "video": null, "description": "Paul Edgecomb se vrací ve vzpomínkách do roku 1935, kdy byl zaměstnán v louisianské věznici jako hlavní dozorce. Tenkrát se tam setkal s výjimečným, byť duchem prostým mužem, který byl obdařen nejen velkým srdcem, ale také nadpozemskými schopnostmi. Byl to John Coffey, neprávem odsouzený na smrt za vraždu dvou malých holčiček. V té době trpěl Paul těžkým zánětem močového měchýře a také neměl šanci zbavit se sadistického, všemi nenáviděného dozorce Percyho. Jednoho dne chce s Paulem mluvit Coffey. Když se k němu přiblíží, chytí ho rukou v rozkroku, pak šokovaného Paula pustí a on uvidí, jak černoch vypustil z úst černý oblak, a současně si uvědomí, že jeho bolestivý zánět zmizel. Coffey má zvláštní schopnost, díky které vyléčí ženu správce věznice, ke které ho tajně v noci převezou, dokonce oživí cvičenou myš jednoho vězně, kterou zabil zlomyslný Percy. John Coffey, kterého čeká smrt, přijímá svůj úděl odevzdaně a bez hořkosti.", "created": "2023-12-14T16:51:17.629Z", "updated": "2023-12-14T16:51:17.629Z", "countries": [], "genres": [], "directors": [], "actors": []}}, {"model": "viewer.movie", "pk": 10, "fields": {"title_orig": "Twelve Angry Men", "title_cz": null, "title_sk": null, "movie_image": "", "year": 1957, "video": null, "description": "Dvanáct porotců má jednomyslně rozhodnout o vině či nevině mladého muže, který je obviněn z vraždy svého otce. Porotci jsou průměrní Američané s obyčejnými zájmy a zaměstnáním. V průběžném hlasování jedenáct hlasuje za vinu, jenom porotce číslo 8 je proti...", "created": "2023-12-14T16:52:33.765Z", "updated": "2023-12-14T16:52:33.765Z", "countries": [], "genres": [], "directors": [], "actors": []}}]